git_story/__init__.py
git_story/__main__.py
git_story/git_story.py
git_story/logo.png
git_story-0.1.4.dist-info/METADATA
git_story-0.1.4.dist-info/WHEEL
git_story-0.1.4.dist-info/entry_points.txt
git_story-0.1.4.dist-info/top_level.txt
git_story-0.1.4.dist-info/RECORD
