Metadata-Version: 2.1
Name: git-story
Version: 0.1.4
Summary: Tell the story of your Git project by creating video animations (.mp4) of your commit history directly from your Git repo.
Home-page: https://initialcommit.com/tools/git-story
Author: Jacob Stopak
Author-email: jacob@initialcommit.io
Project-URL: Homepage, https://initialcommit.com/tools/git-story
Keywords: git story git-story manim animation gitanimation
Classifier: Programming Language :: Python :: 3
Classifier: License :: OSI Approved :: MIT License
Classifier: Operating System :: OS Independent
Requires-Python: >=3.7
Requires-Dist: gitpython
Requires-Dist: manim
